HttpBoot/__init__.py
HttpBoot/extractor.py
HttpBoot/http_boot.py
HttpBoot/locust_boot.py
HttpBoot/locust_main.py
HttpBoot/response_wrapper.py
HttpBoot/validator.py
HttpBoot-1.0.9.dist-info/METADATA
HttpBoot-1.0.9.dist-info/WHEEL
HttpBoot-1.0.9.dist-info/entry_points.txt
HttpBoot-1.0.9.dist-info/top_level.txt
HttpBoot-1.0.9.dist-info/RECORD
