Metadata-Version: 2.1
Name: HttpBoot
Version: 1.0.9
Summary: HttpBoot: make an easy way (yaml) to HTTP(S) API automation testing, also support using yaml to call locust performance test
Home-page: https://github.com/shigebeyond/HttpBoot
Author: shigebeyond
Author-email: 772910474@qq.com
License: BSD
Classifier: Development Status :: 5 - Production/Stable
Classifier: Topic :: Software Development :: Testing
Classifier: Topic :: Software Development :: Quality Assurance
Classifier: Topic :: Software Development :: Libraries :: Python Modules
Classifier: Operating System :: POSIX :: Linux
Classifier: Operating System :: MacOS :: MacOS X
Classifier: Operating System :: Microsoft :: Windows
Classifier: Programming Language :: Python
Classifier: Programming Language :: Python :: 3.7
Classifier: Programming Language :: Python :: 3.8
Classifier: Programming Language :: Python :: 3.9
Requires-Python: >=3.6
Requires-Dist: curlify (==2.2.1)
Requires-Dist: locust (==2.10.1)
Requires-Dist: pyutilb (>=1.0.6)
